cFSPlib/__init__.py
cFSPlib/cFSP.py
cFSPlib/cfsp_cluster.py
cFSPlib/cfsp_debug.py
cFSPlib/cfsp_globals.py
cFSPlib/cfsp_image.py
cFSPlib/cfsp_instance.py
cFSPlib/cfsp_user.py
cFSPlib/cfsp_util.py
cFSPlib/comm.py
cFSPlib/mngmt.py
cFSPlib/util.py
cFSPlib/version.txt
cFSPlib/python_api_client/__init__.py
cFSPlib/python_api_client/setup.py
cFSPlib/python_api_client/swagger_client/__init__.py
cFSPlib/python_api_client/swagger_client/api_client.py
cFSPlib/python_api_client/swagger_client/configuration.py
cFSPlib/python_api_client/swagger_client/rest.py
cFSPlib/python_api_client/swagger_client/api/__init__.py
cFSPlib/python_api_client/swagger_client/api/administration__admin_only_api.py
cFSPlib/python_api_client/swagger_client/api/clusters_api.py
cFSPlib/python_api_client/swagger_client/api/debug_api.py
cFSPlib/python_api_client/swagger_client/api/images_api.py
cFSPlib/python_api_client/swagger_client/api/instances_api.py
cFSPlib/python_api_client/swagger_client/api/mantle_architecture_api.py
cFSPlib/python_api_client/swagger_client/api/projects_api.py
cFSPlib/python_api_client/swagger_client/api/resources__admin_only_api.py
cFSPlib/python_api_client/swagger_client/models/__init__.py
cFSPlib/python_api_client/swagger_client/models/administration_mantle_logic_body.py
cFSPlib/python_api_client/swagger_client/models/administration_platform_logic_body.py
cFSPlib/python_api_client/swagger_client/models/build_script.py
cFSPlib/python_api_client/swagger_client/models/cluster.py
cFSPlib/python_api_client/swagger_client/models/cluster_id_node_id_body.py
cFSPlib/python_api_client/swagger_client/models/clusters_body.py
cFSPlib/python_api_client/swagger_client/models/image.py
cFSPlib/python_api_client/swagger_client/models/images_app_logic_body.py
cFSPlib/python_api_client/swagger_client/models/images_body.py
cFSPlib/python_api_client/swagger_client/models/inline_response200.py
cFSPlib/python_api_client/swagger_client/models/inline_response2001.py
cfsp-0.1.17.dist-info/LICENSE
cfsp-0.1.17.dist-info/METADATA
cfsp-0.1.17.dist-info/NOTICE
cfsp-0.1.17.dist-info/WHEEL
cfsp-0.1.17.dist-info/top_level.txt
cfsp-0.1.17.dist-info/RECORD
