Metadata-Version: 2.1
Name: cfsp
Version: 0.1.17
Summary: The cloudFPGA Support Package
Home-page: https://github.com/cloudFPGA/cfsp
Author: Dionysios Diamantopoulos
Author-email: did@zurich.ibm.com
License: UNKNOWN
Project-URL: Bug Tracker, https://github.com/cloudFPGA/cfsp/issues
Platform: UNKNOWN
Classifier: Intended Audience :: Developers
Classifier: License :: OSI Approved :: Apache Software License
Classifier: Programming Language :: Python :: 3
Classifier: Topic :: Software Development :: Libraries :: Python Modules
Requires-Python: >=3.6
License-File: LICENSE
License-File: NOTICE
Requires-Dist: certifi
Requires-Dist: charset-normalizer
Requires-Dist: docopt
Requires-Dist: idna
Requires-Dist: prompt-toolkit
Requires-Dist: Pygments
Requires-Dist: PyInquirer
Requires-Dist: regex
Requires-Dist: requests
Requires-Dist: six
Requires-Dist: tqdm
Requires-Dist: urllib3
Requires-Dist: wcwidth
